README.md
setup.py
OhMyDecorators/Concurrency.py
OhMyDecorators/DevQol.py
OhMyDecorators/ErrorHandling.py
OhMyDecorators/TypeConverters.py
OhMyDecorators/__init__.py
OhMyDecorators.egg-info/PKG-INFO
OhMyDecorators.egg-info/SOURCES.txt
OhMyDecorators.egg-info/dependency_links.txt
OhMyDecorators.egg-info/requires.txt
OhMyDecorators.egg-info/top_level.txt