Metadata-Version: 2.1
Name: OhMyDecorators
Version: 0.1.0
Summary: A Python library that provides lots of decorators for simple tasks.
Home-page: https://github.com/A-Boring-Square/OhMyDecorators
Author: A-Boring-Square
Author-email: aboringsquare@gmail.com
Classifier: Programming Language :: Python :: 3
Classifier: License :: OSI Approved :: MIT License
Classifier: Operating System :: OS Independent
Requires-Python: >=3.6
Requires-Dist: tensorflow
